prosecco/__init__.py
prosecco/model.py
prosecco/normalizer.py
prosecco/data/en/suffix.txt
prosecco/data/pl/bye.txt
prosecco/data/pl/hi.txt
prosecco/data/pl/prefix.txt
prosecco/data/pl/preposition.txt
prosecco/data/pl/pronoun.txt
prosecco/data/pl/stopwords.txt
prosecco/data/pl/suffix.txt
prosecco/data/pl/swear.txt
prosecco/data/pl/thx.txt
prosecco/example/advanced.py
prosecco/example/basic.py
prosecco/example/custom_condition_class.py
prosecco/example/qa.py
prosecco/example/superhero.txt
prosecco-0.0.7.dist-info/LICENSE
prosecco-0.0.7.dist-info/METADATA
prosecco-0.0.7.dist-info/WHEEL
prosecco-0.0.7.dist-info/top_level.txt
prosecco-0.0.7.dist-info/RECORD
