Metadata-Version: 2.1
Name: prosecco
Version: 0.0.7
Summary: Simple, extendable nlp engine that can extract data based on provided conditions.
Home-page: https://github.com/vane/prosecco
Author: Michal Szczepanski
Author-email: michal@vane.pl
License: MIT
Platform: UNKNOWN
Classifier: Development Status :: 3 - Alpha
Classifier: Intended Audience :: Developers
Classifier: Programming Language :: Python :: 2
Classifier: Programming Language :: Python :: 3
Classifier: Operating System :: OS Independent
Classifier: License :: OSI Approved :: MIT License
